CHANGELOG.rst
MANIFEST.in
README.rst
setup.cfg
setup.py
src/kids/__init__.py
src/kids.test.egg-info/PKG-INFO
src/kids.test.egg-info/SOURCES.txt
src/kids.test.egg-info/dependency_links.txt
src/kids.test.egg-info/requires.txt
src/kids.test.egg-info/top_level.txt
src/kids/test/__init__.py